spectralib/__init__.py
spectralib/filterbank.py
spectralib/frb.py
spectralib/pulsar.py
spectralib/rfi.py
spectralib/search.py
tests/__init__.py
tests/benchmark.py
tests/test_filterbank.py
tests/test_frb.py
tests/test_pulsar.py
tests/test_rfi.py
spectralib-0.0.24.dist-info/LICENSE
spectralib-0.0.24.dist-info/METADATA
spectralib-0.0.24.dist-info/WHEEL
spectralib-0.0.24.dist-info/top_level.txt
spectralib-0.0.24.dist-info/RECORD
