Metadata-Version: 2.1
Name: spectralib
Version: 0.0.24
Summary: Synthetic Pulsar Emission, Contamination and Transients Radio Astronomy Library (SPECTRALib)
Home-page: https://github.com/jack-white1/spectralib
Author: Jack White
Author-email: jack.white@eng.ox.ac.uk
License: UNKNOWN
Platform: UNKNOWN
Classifier: Development Status :: 1 - Planning
